darshika_khandelwal/__init__.py
darshika_khandelwal/__main__.py
darshika_khandelwal/names.txt
darshika_khandelwal/speaker.py
darshika_khandelwal/speakers/__init__.py
darshika_khandelwal/speakers/darshika.py
darshika_khandelwal-0.3.0.dist-info/licenses/license.txt
darshika_khandelwal-0.3.0.dist-info/METADATA
darshika_khandelwal-0.3.0.dist-info/WHEEL
darshika_khandelwal-0.3.0.dist-info/entry_points.txt
darshika_khandelwal-0.3.0.dist-info/top_level.txt
darshika_khandelwal-0.3.0.dist-info/RECORD
