Metadata-Version: 2.4
Name: darshika_khandelwal
Version: 0.3.0
Summary: My first package!
Author-email: Justin Furuness <jfuruness@gmail.com>
Maintainer-email: Justin Furuness <jfuruness@gmail.com>
License: COPYRIGHT 2025 Darshika Khandelwal
Project-URL: Homepage, https://github.com/jfuruness/darshika_khandelwal
Project-URL: Documentation, https://github.com/jfuruness/darshika_khandelwal/README.md
Keywords: Furuness
Classifier: Programming Language :: Python :: 3.9
Classifier: Programming Language :: Python :: Implementation :: CPython
Classifier: License :: OSI Approved :: BSD License
Classifier: Intended Audience :: Developers
Classifier: Operating System :: POSIX :: Linux
Classifier: Operating System :: Microsoft :: Windows
Classifier: Operating System :: MacOS
Classifier: Operating System :: MacOS :: MacOS X
Requires-Python: >=3.9
License-File: license.txt
Requires-Dist: colorama~=0.0
Provides-Extra: dev
Requires-Dist: twine; extra == "dev"
Requires-Dist: build; extra == "dev"
Dynamic: license-file
